{"categories":{"preraid":{"hunter_bm":{"rangedAttackPower":1.0,"agility":1.94,"rangedCritRating":1.58,"physicalHasteRating":2.17,"armorPen":0.26,"redSocket":19.4,"yellowSocket":15.8,"blueSocket":9.7,"metaSocket":100.0},"hunter_surv":{"rangedAttackPower":1.0,"agility":2.64,"rangedCritRating":1.35,"physicalHasteRating":1.05,"armorPen":0.28,"redSocket":26.41,"yellowSocket":13.5,"blueSocket":13.21,"metaSocket":100.0},"mage_arcane":{"spellDamage":1.0,"intellect":0.76,"spellHasteRating":0.57,"spellCritRating":0.86,"spellHitRating":0.05,"redSocket":12.0,"yellowSocket":8.85,"blueSocket":6.0,"metaSocket":100.0},"mage_fire":{"spellDamage":1.0,"intellect":0.3,"spellHasteRating":0.15,"spellCritRating":0.72,"spellHitRating":0.11,"redSocket":12.0,"yellowSocket":6.75,"blueSocket":6.0,"metaSocket":100.0},"mage_frost":{"spellDamage":1.0,"intellect":0.21,"spellHasteRating":0.0,"spellCritRating":0.65,"spellHitRating":0.0,"redSocket":12.0,"yellowSocket":6.0,"blueSocket":6.0,"metaSocket":100.0},"rogue_assassination":{"attackPower":1.0,"strength":1.18,"agility":2.09,"meleeCritRating":1.61,"physicalHasteRating":1.63,"expertiseRating":3.08,"armorPen":0.31,"physicalHitRating":0.09,"redSocket":20.9,"yellowSocket":10.45,"blueSocket":10.45,"metaSocket":100.0},"rogue_combat":{"attackPower":1.0,"strength":1.08,"agility":2.18,"meleeCritRating":1.51,"physicalHasteRating":1.37,"expertiseRating":3.2,"armorPen":0.25,"physicalHitRating":1.14,"redSocket":21.8,"yellowSocket":10.9,"blueSocket":10.9,"metaSocket":100.0},"shaman_ele":{"spellDamage":1.0,"intellect":0.26,"spellHasteRating":1.22,"spellCritRating":0.68,"spellHitRating":0.09,"redSocket":12.0,"yellowSocket":9.4,"blueSocket":6.0,"metaSocket":100.0},"shaman_enh":{"attackPower":1.0,"strength":1.06,"agility":2.79,"meleeCritRating":1.56,"physicalHasteRating":1.22,"expertiseRating":3.29,"armorPen":0.26,"physicalHitRating":1.76,"spellCritRating":0.03,"spellHitRating":0.52,"spellDamage":0.36,"redSocket":10.61,"yellowSocket":13.11,"blueSocket":5.31,"metaSocket":100.0},"warlock_affliction_ruin":{"spellDamage":1.0,"intellect":0.3,"spellHasteRating":1.06,"spellCritRating":0.68,"spellHitRating":1.23,"redSocket":12.0,"yellowSocket":12.15,"blueSocket":6.0,"metaSocket":100.0},"warlock_affliction_ua":{"spellDamage":1.0,"intellect":0.25,"spellHasteRating":1.43,"spellCritRating":0.34,"spellHitRating":1.18,"redSocket":12.0,"yellowSocket":11.9,"blueSocket":6.0,"metaSocket":100.0},"warlock_destruction_fire":{"spellDamage":1.0,"intellect":0.48,"spellHasteRating":1.47,"spellCritRating":0.57,"spellHitRating":0.89,"redSocket":12.0,"yellowSocket":10.45,"blueSocket":6.0,"metaSocket":100.0},"warlock_destruction_shadow":{"spellDamage":1.0,"intellect":0.45,"spellHasteRating":1.1,"spellCritRating":0.75,"spellHitRating":1.53,"redSocket":12.0,"yellowSocket":13.65,"blueSocket":6.0,"metaSocket":100.0},"warrior_arms":{"attackPower":1.0,"strength":1.17,"agility":2.7,"meleeCritRating":2.31,"physicalHasteRating":3.25,"expertiseRating":4.2,"armorPen":0.32,"redSocket":11.7,"yellowSocket":23.1,"blueSocket":5.85,"metaSocket":100.0},"warrior_fury":{"attackPower":1.0,"strength":1.06,"agility":2.7,"meleeCritRating":2.0,"physicalHasteRating":1.78,"expertiseRating":3.4,"armorPen":0.3,"physicalHitRating":1.43,"redSocket":10.61,"yellowSocket":20.0,"blueSocket":5.31,"metaSocket":100.0}}},"options":{"hunter_bm":{"benefitsFromMeleeWeaponDps":false,"benefitsFromRangedWeaponDps":true},"hunter_surv":{"benefitsFromMeleeWeaponDps":false,"benefitsFromRangedWeaponDps":true},"mage_arcane":{"benefitsFromMeleeWeaponDps":false,"benefitsFromRangedWeaponDps":false},"mage_fire":{"benefitsFromMeleeWeaponDps":false,"benefitsFromRangedWeaponDps":false},"mage_frost":{"benefitsFromMeleeWeaponDps":false,"benefitsFromRangedWeaponDps":false},"rogue_assassination":{"benefitsFromMeleeWeaponDps":true,"benefitsFromRangedWeaponDps":false},"rogue_combat":{"benefitsFromMeleeWeaponDps":true,"benefitsFromRangedWeaponDps":false},"shaman_ele":{"benefitsFromMeleeWeaponDps":false,"benefitsFromRangedWeaponDps":false},"shaman_enh":{"benefitsFromMeleeWeaponDps":true,"benefitsFromRangedWeaponDps":false},"warlock_affliction_ruin":{"benefitsFromMeleeWeaponDps":false,"benefitsFromRangedWeaponDps":false},"warlock_affliction_ua":{"benefitsFromMeleeWeaponDps":false,"benefitsFromRangedWeaponDps":false},"warlock_destruction_fire":{"benefitsFromMeleeWeaponDps":false,"benefitsFromRangedWeaponDps":false},"warlock_destruction_shadow":{"benefitsFromMeleeWeaponDps":false,"benefitsFromRangedWeaponDps":false},"warrior_arms":{"benefitsFromMeleeWeaponDps":true,"benefitsFromRangedWeaponDps":false},"warrior_fury":{"benefitsFromMeleeWeaponDps":true,"benefitsFromRangedWeaponDps":false}}}